cthun_client/__init__.py
cthun_client/client.py
cthun_client/common.py
cthun_client/config.py
cthun_client/connection.py
cthun_client/exception.py
cthun_client/device/__init__.py
cthun_client/device/android.py
cthun_client/device/device_base.py
cthun_client/device/ios.py
python_cthun_client-0.1.3.dist-info/METADATA
python_cthun_client-0.1.3.dist-info/WHEEL
python_cthun_client-0.1.3.dist-info/top_level.txt
python_cthun_client-0.1.3.dist-info/RECORD
