Metadata-Version: 2.1
Name: python-cthun-client
Version: 0.1.3
Summary: test
Home-page: https://github.com/Jason916/python-cthun-client
Author: Jason916
Author-email: Jason1989Xu@gmail.com
License: UNKNOWN
Platform: UNKNOWN
Classifier: Programming Language :: Python
Classifier: Topic :: Software Development :: Testing
Requires-Dist: requests (==2.*)
